isomarker/isomarker.py
IsoMarker-0.7.0.dist-info/LICENSE
IsoMarker-0.7.0.dist-info/METADATA
IsoMarker-0.7.0.dist-info/WHEEL
IsoMarker-0.7.0.dist-info/top_level.txt
IsoMarker-0.7.0.dist-info/RECORD
